{
    "Wednesday 23rd April 2025 - Schedule Time UK GMT": {
        "TV Shows</span>": [
            {
                "time": "12:00",
                "event": "Super Animals Season 2, Episode 3",
                "channels": []
            },
            {
                "time": "15:00",
                "event": "The Price Is Right Season 53, Episode 139",
                "channels": []
            },
            {
                "time": "15:00",
                "event": "The Jennifer Hudson Show Season 3, Episode 160",
                "channels": []
            },
            {
                "time": "16:00",
                "event": "The Steve Wilkos Show Season 18, Episode 102",
                "channels": []
            },
            {
                "time": "16:00",
                "event": "Elinor Wonders Why Season 2, Episode 15",
                "channels": []
            },
            {
                "time": "18:00",
                "event": "Beyond the Gates Season 1, Episode 41",
                "channels": []
            },
            {
                "time": "18:00",
                "event": "Pictionary Season 3, Episode 133",
                "channels": []
            },
            {
                "time": "19:00",
                "event": "The Kelly Clarkson Show Season 6, Episode 137",
                "channels": []
            },
            {
                "time": "19:00",
                "event": "General Hospital Season 62, Episode 157",
                "channels": []
            },
            {
                "time": "21:00",
                "event": "FanDuel Racing Live",
                "channels": []
            },
            {
                "time": "23:00",
                "event": "Tyler Perry's Young Dylan Season 5, Episode 5",
                "channels": []
            },
            {
                "time": "23:00",
                "event": "Jeopardy! Season 41, Episode 163",
                "channels": []
            },
            {
                "time": "00:00",
                "event": "Pap\u00e1s por conveniencia Season 1, Episode 65",
                "channels": []
            },
            {
                "time": "00:00",
                "event": "Wild Cards Season 2, Episode 12",
                "channels": []
            },
            {
                "time": "00:00",
                "event": "The Conners Season 7, Episode 5",
                "channels": []
            },
            {
                "time": "00:00",
                "event": "The Masked Singer Season 13, Episode 11",
                "channels": []
            },
            {
                "time": "00:00",
                "event": "Chicago Med Season 10, Episode 19",
                "channels": []
            },
            {
                "time": "00:00",
                "event": "Survivor Season 48, Episode 9",
                "channels": []
            },
            {
                "time": "00:00",
                "event": "La casa de los famosos: All-stars",
                "channels": []
            },
            {
                "time": "00:00",
                "event": "Dr. Pimple Popper Season 9",
                "channels": []
            },
            {
                "time": "00:00",
                "event": "Ridiculousness Season 43, Episode 16",
                "channels": []
            },
            {
                "time": "00:30",
                "event": "The Conners Season 7, Episode 6 \u2022 Finale",
                "channels": []
            },
            {
                "time": "01:00",
                "event": "The Floor Season 3, Episode 12 \u2022 Finale",
                "channels": []
            },
            {
                "time": "01:00",
                "event": "Chicago Fire Season 13, Episode 19",
                "channels": []
            },
            {
                "time": "01:00",
                "event": "Celebrity Jeopardy! Season 3, Episode 13 \u2022 Finale",
                "channels": []
            },
            {
                "time": "01:00",
                "event": "Sherlock & Daughter Season 1, Episode 2",
                "channels": []
            },
            {
                "time": "01:00",
                "event": "PAYBACK Season 4, Episode 1 \u2022 Premiere",
                "channels": []
            },
            {
                "time": "01:00",
                "event": "Bitchin' Rides Season 11, Episode 6",
                "channels": []
            },
            {
                "time": "01:00",
                "event": "Expedition Files Season 2, Episode 2",
                "channels": []
            },
            {
                "time": "01:00",
                "event": "American Pickers Season 26",
                "channels": []
            },
            {
                "time": "01:00",
                "event": "Stadium Lockup Season 1, Episode 6",
                "channels": []
            },
            {
                "time": "01:00",
                "event": "Guy's Grocery Games Season 36",
                "channels": []
            },
            {
                "time": "01:00",
                "event": "Married to Real Estate Season 4, Episode 7",
                "channels": []
            },
            {
                "time": "01:00",
                "event": "Summer House Season 9, Episode 11",
                "channels": []
            },
            {
                "time": "01:00",
                "event": "Border Security: Australia's Front Line Season 15, Episode 1",
                "channels": []
            },
            {
                "time": "01:00",
                "event": "All the Queen's Men Season 3, Episode 6",
                "channels": []
            },
            {
                "time": "01:30",
                "event": "The Amazing Race Season 37, Episode 8",
                "channels": []
            },
            {
                "time": "02:00",
                "event": "Chicago P.D. Season 12, Episode 19",
                "channels": []
            },
            {
                "time": "02:00",
                "event": "Andor Season 2, Episode 1 \u2022 Premiere",
                "channels": []
            },
            {
                "time": "02:00",
                "event": "Changing Planet Season 4, Episode 1 \u2022 Premiere",
                "channels": []
            },
            {
                "time": "02:00",
                "event": "Fix My Frankenhouse Season 2, Episode 5",
                "channels": []
            },
            {
                "time": "02:00",
                "event": "Booked: First Day In Season 3, Episode 6",
                "channels": []
            },
            {
                "time": "02:00",
                "event": "Life or Death: The Negotiators Season 1, Episode 1",
                "channels": []
            },
            {
                "time": "02:00",
                "event": "Ghost Adventures Season 29, Episode 2",
                "channels": []
            },
            {
                "time": "02:00",
                "event": "The Stolen Girl Season 1, Episode 2",
                "channels": []
            },
            {
                "time": "02:30",
                "event": "Pound 4 Pound Season 1, Episode 9",
                "channels": []
            },
            {
                "time": "03:00",
                "event": "Mysteries of the Abandoned: Hidden America Season 4, Episode 1",
                "channels": []
            }
        ],
        "Soccer</span>": [
            {
                "time": "07:30",
                "event": "China - League 1 : Foshan Nanshi vs Jiangxi Dingnan United",
                "channels": []
            },
            {
                "time": "09:00",
                "event": "Australia - NPL - Queensland : Olympic FC vs Wynnum Wolves",
                "channels": []
            },
            {
                "time": "10:00",
                "event": "Japan - J3 League : Fukushima United vs Azul Claro Numazu",
                "channels": []
            },
            {
                "time": "10:30",
                "event": "South Korea - K League 1 : Anyang vs Ulsan HD",
                "channels": []
            },
            {
                "time": "11:00",
                "event": "India - Supercupa : Bengaluru vs Inter Kashi",
                "channels": []
            },
            {
                "time": "11:00",
                "event": "Thailand - Cup FA : Ratchaburi Mitr Phol vs Phrae United",
                "channels": []
            },
            {
                "time": "11:00",
                "event": "Thailand - Cup FA : Sukhothai vs Muangthong United",
                "channels": []
            },
            {
                "time": "11:30",
                "event": "China - League 1 : Guangxi Pingguo Haliao vs Guandong GZ Power",
                "channels": []
            },
            {
                "time": "11:30",
                "event": "China - League 1 : Shijiazhuang Gongfu vs Suzhou Dongwu",
                "channels": []
            },
            {
                "time": "12:00",
                "event": "Thailand - Cup FA : Nakhon Ratchasima vs BG Pathum United",
                "channels": []
            },
            {
                "time": "13:00",
                "event": "Croatia - 1. HNL : Gorica vs Dinamo Zagreb",
                "channels": []
            },
            {
                "time": "13:00",
                "event": "Azerbaijan - Az\u0259rbaycan Kuboku : Qaraba\u011f vs Araz",
                "channels": []
            },
            {
                "time": "13:55",
                "event": "EAU - Pro League : Al Bataeh vs Al Wasl",
                "channels": []
            },
            {
                "time": "13:55",
                "event": "EAU - Pro League : Al Jazira vs Ittihad Kalba",
                "channels": []
            },
            {
                "time": "14:00",
                "event": "Serbia - Super Liga : Novi Pazar vs Vojvodina",
                "channels": []
            },
            {
                "time": "14:00",
                "event": "Serbia - Prva Liga : Mladost Novi Sad vs Radnik Surdulica",
                "channels": []
            },
            {
                "time": "14:00",
                "event": "Bosnia and Herzegovina Premijer Liga : FK Sloboda Tuzla vs. HSK Zrinjski Mostar",
                "channels": []
            },
            {
                "time": "14:30",
                "event": "India - Supercupa : Mumbai City vs Chennaiyin",
                "channels": []
            },
            {
                "time": "15:00",
                "event": "Greece - Super League : Panserraikos vs Panaitolikos",
                "channels": []
            },
            {
                "time": "15:00",
                "event": "Greece - Super League : Lamia vs Volos NFC",
                "channels": []
            },
            {
                "time": "15:00",
                "event": "Finland - Veikkausliiga : KuPS vs Mariehamn",
                "channels": []
            },
            {
                "time": "15:00",
                "event": "Estonia - Meistriliiga : Parnu Vaprus vs Narva Trans",
                "channels": []
            },
            {
                "time": "15:30",
                "event": "Croatia - 1. HNL : Hajduk Split vs Istra 1961",
                "channels": []
            },
            {
                "time": "15:55",
                "event": "Saudi Arabia - Pro League : Al Riyadh vs Al Fateh",
                "channels": []
            },
            {
                "time": "16:00",
                "event": "Serbia - Super Liga : Partizan vs OFK Beograd",
                "channels": []
            },
            {
                "time": "16:00",
                "event": "Saudi Arabia - SAFF Women's Cup : Al-nassr vs Al-taraji",
                "channels": []
            },
            {
                "time": "16:00",
                "event": "Azerbaijan - Az\u0259rbaycan Kuboku : Sabah vs Neft\u00e7i",
                "channels": []
            },
            {
                "time": "16:00",
                "event": "Bulgaria - Bulgarian Cup : Ludogorets vs Botev Vratsa",
                "channels": []
            },
            {
                "time": "16:00",
                "event": "Bosnia and Herzegovina Premijer Liga : NK Siroki Brijeg vs. NK Gosk Gabela",
                "channels": []
            },
            {
                "time": "16:00",
                "event": "Slovenian Cup : Koper vs Bravo",
                "channels": []
            },
            {
                "time": "16:00",
                "event": "Poland - I League : Odra Opole vs Stal Rzeszow",
                "channels": []
            },
            {
                "time": "16:00",
                "event": "Estonia - Meistriliiga : Paide Linnameeskond vs Levadia Tallinn",
                "channels": []
            },
            {
                "time": "16:00",
                "event": "Finland - Veikkausliiga : SJK Seinajoki vs AC Oulu",
                "channels": []
            },
            {
                "time": "16:00",
                "event": "Slovakia - 1. liga - Gr. Championship : Zilina vs FC Kosice",
                "channels": []
            },
            {
                "time": "16:10",
                "event": "Saudi Arabia - Pro League : Al Kholood vs Al Akhdoud",
                "channels": []
            },
            {
                "time": "16:30",
                "event": "Italy Serie A : Torino vs Udinese",
                "channels": []
            },
            {
                "time": "16:30",
                "event": "Italy Serie A : Cagliari vs Fiorentina",
                "channels": []
            },
            {
                "time": "16:30",
                "event": "Italy Serie A : Genoa vs Lazio",
                "channels": []
            },
            {
                "time": "16:30",
                "event": "Italy Serie A : Parma vs Juventus",
                "channels": []
            },
            {
                "time": "16:30",
                "event": "Romania - Cupa Romaniei : Hermannstadt vs Rapid Bucure\u015fti",
                "channels": []
            },
            {
                "time": "16:30",
                "event": "Austria - Football Bundesliga : Simulcast",
                "channels": []
            },
            {
                "time": "16:30",
                "event": "Austria - Football Bundesliga : Salzburg vs Wolfsberger AC",
                "channels": []
            },
            {
                "time": "16:30",
                "event": "Austria - Football Bundesliga : Blau-Wei\u00df Linz vs Rapid Wien",
                "channels": []
            },
            {
                "time": "16:45",
                "event": "EAU - Pro League : Shabab Al Ahli vs Al Khaleej Khor Fakkan",
                "channels": []
            },
            {
                "time": "17:00",
                "event": "Serbia - Super Liga : Radni\u010dki Kragujevac vs Crvena Zvezda",
                "channels": []
            },
            {
                "time": "17:00",
                "event": "Spain- La Liga : Athletic Club vs Las Palmas",
                "channels": []
            },
            {
                "time": "17:00",
                "event": "Spain- La Liga : Celta de Vigo vs Villarreal",
                "channels": []
            },
            {
                "time": "17:00",
                "event": "Sweden - Allsvenskan : Hammarby vs Malm\u00f6 FF",
                "channels": []
            },
            {
                "time": "17:00",
                "event": "Sweden - Allsvenskan : Elfsborg vs Sirius",
                "channels": []
            },
            {
                "time": "17:00",
                "event": "Sweden - Allsvenskan : Hacken vs Degerfors",
                "channels": []
            },
            {
                "time": "17:00",
                "event": "Sweden - Allsvenskan : Halmstads vs Mjallby",
                "channels": []
            },
            {
                "time": "17:00",
                "event": "Czech - Cup : Sparta Praga vs Viktoria Plzen",
                "channels": []
            },
            {
                "time": "17:30",
                "event": "Greece - Super League : Kallithea vs Levadiakos",
                "channels": []
            },
            {
                "time": "18:00",
                "event": "Croatia - 1. HNL : Rijeka vs Osijek",
                "channels": []
            },
            {
                "time": "18:00",
                "event": "Hungary - Magyar Kupa : Ferencv\u00e1ros vs MTK",
                "channels": []
            },
            {
                "time": "18:00",
                "event": "Netherlands - Eredivisie : Groningen vs Heracles",
                "channels": []
            },
            {
                "time": "18:00",
                "event": "Saudi Arabia - Pro League : Al Khaleej vs Al Quadisiya",
                "channels": []
            },
            {
                "time": "18:15",
                "event": "England - Women's Super League : Chelsea FC vs Crystal Palace",
                "channels": []
            },
            {
                "time": "18:30",
                "event": "Austria - Football Bundesliga : Austria Wien vs Sturm Graz",
                "channels": []
            },
            {
                "time": "18:30",
                "event": "Belgium - Pro League : Antwerp vs Genk",
                "channels": []
            },
            {
                "time": "18:30",
                "event": "Belgium - Pro League : Anderlecht vs Gent",
                "channels": []
            },
            {
                "time": "18:45",
                "event": "Bosnia and Herzegovina Premijer Liga : FK Zeljeznicar Sarajevo vs. FK Borac Banja Luka",
                "channels": []
            },
            {
                "time": "19:00",
                "event": "England - Premier League : Arsenal vs Crystal Palace",
                "channels": []
            },
            {
                "time": "19:00",
                "event": "Coppa Italia : Internazionale vs Milan",
                "channels": []
            },
            {
                "time": "19:00",
                "event": "France - Premi\u00e8re Ligue : Simulcast",
                "channels": []
            },
            {
                "time": "19:00",
                "event": "France - Premi\u00e8re Ligue : Montpellier vs Dijon",
                "channels": []
            },
            {
                "time": "19:00",
                "event": "France - Premi\u00e8re Ligue : Paris vs Fleury 91",
                "channels": []
            },
            {
                "time": "19:15",
                "event": "Iceland Efsta deild : Breidablik K\u00f3pavogur vs Stjarnan Gar\u00f0ab\u00e6r",
                "channels": []
            },
            {
                "time": "19:15",
                "event": "Ta\u00e7a de Portugal : Benfica vs Tirsense",
                "channels": []
            },
            {
                "time": "19:30",
                "event": "Spain- La Liga : Getafe vs Real Madrid",
                "channels": []
            },
            {
                "time": "19:30",
                "event": "Spain- La Liga : Deportivo Alav\u00e9s vs Real Sociedad",
                "channels": []
            },
            {
                "time": "20:30",
                "event": "Ecuador - Serie B : Gualaceo vs San Antonio",
                "channels": []
            },
            {
                "time": "20:30",
                "event": "Ecuador - Serie B : Leones del Norte vs CA Vinotinto",
                "channels": []
            },
            {
                "time": "21:00",
                "event": "MLS Next Pro : New England Revolution II vs Columbus Crew II",
                "channels": []
            },
            {
                "time": "21:00",
                "event": "Campeonato Brasileiro De Futebol Sub-20 : Vasco vs S\u00e3o Paulo",
                "channels": []
            },
            {
                "time": "21:45",
                "event": "Copa Sudamericana : Huracan vs America De Cali",
                "channels": []
            },
            {
                "time": "22:00",
                "event": "Copa Libertadores : San Antonio Bulo Bulo vs V\u00e9lez Sarsfield",
                "channels": []
            },
            {
                "time": "22:00",
                "event": "Copa Libertadores : Olimpia vs Pe\u00f1arol",
                "channels": []
            },
            {
                "time": "22:00",
                "event": "Copa Sudamericana : Uni\u00f3n Espa\u00f1ola vs Fluminense",
                "channels": []
            },
            {
                "time": "22:00",
                "event": "Copa Sudamericana : Hurac\u00e1n vs Am\u00e9rica de Cali",
                "channels": []
            },
            {
                "time": "22:00",
                "event": "MLS Next Pro : Real Monarchs vs Los Angeles FC II",
                "channels": []
            },
            {
                "time": "23:00",
                "event": "MLS Next Pro : Sporting Kansas City II vs Tacoma Defiance",
                "channels": []
            },
            {
                "time": "23:30",
                "event": "MLS Next Pro : Atlanta United II vs Carolina Core FC",
                "channels": []
            },
            {
                "time": "23:30",
                "event": "MLS Next Pro : New York City II vs Philadelphia Union II",
                "channels": []
            },
            {
                "time": "00:00",
                "event": "Colombia Primera B Apertura : Barranquilla vs Deportes Quindio",
                "channels": []
            },
            {
                "time": "00:30",
                "event": "USL Championship : San Antonio vs Colorado Springs",
                "channels": []
            },
            {
                "time": "00:30",
                "event": "Copa Libertadores : Libertad vs S\u00e3o Paulo",
                "channels": []
            },
            {
                "time": "00:30",
                "event": "Copa Libertadores : Independiente del Valle vs River Plate",
                "channels": []
            },
            {
                "time": "00:30",
                "event": "Copa Libertadores : Estudiantes vs Botafogo",
                "channels": []
            },
            {
                "time": "00:30",
                "event": "Copa Sudamericana : Caracas vs Atl\u00e9tico Mineiro",
                "channels": []
            },
            {
                "time": "00:30",
                "event": "Copa Sudamericana : Vit\u00f3ria vs Cerro Largo",
                "channels": []
            },
            {
                "time": "00:30",
                "event": "MLS Next Pro : North Texas vs The Town FC",
                "channels": []
            },
            {
                "time": "01:00",
                "event": "MLS Next Pro : Vancouver Whitecaps II vs Houston Dynamo II",
                "channels": []
            },
            {
                "time": "01:10",
                "event": "Mexico League de Expansion MX Clausura : CA Morelia vs Atlante",
                "channels": []
            },
            {
                "time": "02:00",
                "event": "CONCACAF Champions Cup : Tigres UANL vs Cruz Azul",
                "channels": []
            },
            {
                "time": "02:00",
                "event": "Copa Libertadores : Atl\u00e9tico Bucaramanga vs Fortaleza",
                "channels": []
            },
            {
                "time": "02:00",
                "event": "Copa Sudamericana : Atl\u00e9tico Grau vs Sportivo Luque\u00f1o",
                "channels": []
            },
            {
                "time": "02:00",
                "event": "Copa Sudamericana : Mushuc Runa vs Uni\u00f3n Santa Fe",
                "channels": []
            },
            {
                "time": "02:00",
                "event": "MLS Next Pro : Ventura County FC vs Portland Timbers II",
                "channels": []
            },
            {
                "time": "03:00",
                "event": "Mexicano Femenino Primera Divisi\u00f3n : Ju\u00e1rez vs. Am\u00e9rica",
                "channels": []
            }
        ],
        "Cricket</span>": [
            {
                "time": "06:00",
                "event": "List-A - Tri-Series : Afghanistan A vs Sri Lanka A",
                "channels": []
            },
            {
                "time": "14:00",
                "event": "Indian Premier League : Sunrisers Hyderabad vs Mumbai Indians",
                "channels": []
            },
            {
                "time": "14:00",
                "event": "Pakistan Super League : Multan Sultans vs Islamabad United",
                "channels": []
            }
        ],
        "Tennis ATP - MADRID</span>": [
            {
                "time": "09:00",
                "event": "ATP - MADRID : Cina F. vs Wong C.",
                "channels": []
            },
            {
                "time": "09:00",
                "event": "ATP - MADRID : Mpetshi Perricard G. vs Navone M.",
                "channels": []
            },
            {
                "time": "10:30",
                "event": "ATP - MADRID : Safiullin R. vs Rinderknech A.",
                "channels": []
            },
            {
                "time": "10:30",
                "event": "ATP - MADRID : Bonzi B. vs Cilic M.",
                "channels": []
            },
            {
                "time": "12:00",
                "event": "ATP - MADRID : Borges N. vs Carreno-Busta P.",
                "channels": []
            },
            {
                "time": "12:00",
                "event": "ATP - MADRID : O'Connell C. vs Ugo Carabelli C.",
                "channels": []
            },
            {
                "time": "13:30",
                "event": "ATP - MADRID : Bautista-Agut R. vs Munar J.",
                "channels": []
            },
            {
                "time": "13:30",
                "event": "ATP - MADRID : Lajovic D. vs Quinn E.",
                "channels": []
            },
            {
                "time": "15:00",
                "event": "ATP - MADRID : Moutet C. vs Mayot H.",
                "channels": []
            },
            {
                "time": "15:00",
                "event": "ATP - MADRID : Fognini F. vs Djere L.",
                "channels": []
            },
            {
                "time": "15:00",
                "event": "ATP - MADRID : Michelsen A. vs Bublik A.",
                "channels": []
            },
            {
                "time": "15:00",
                "event": "ATP - MADRID : Ofner S. vs Gaston H.",
                "channels": []
            },
            {
                "time": "15:00",
                "event": "ATP - MADRID : Comesana F. vs Martinez P.",
                "channels": []
            },
            {
                "time": "15:00",
                "event": "ATP - MADRID : Cerundolo J. M. vs Kovacevic A.",
                "channels": []
            },
            {
                "time": "15:00",
                "event": "ATP - MADRID : Marozsan F. vs Cobolli F.",
                "channels": []
            },
            {
                "time": "15:00",
                "event": "ATP - MADRID : Monfils G. vs Gojo B.",
                "channels": []
            }
        ],
        "Tennis WTA - MADRID</span>": [
            {
                "time": "09:00",
                "event": "WTA - MADRID : Joint M. vs Martinez Cirez C.",
                "channels": []
            },
            {
                "time": "09:00",
                "event": "WTA - MADRID : Parry D. vs Begu I.",
                "channels": []
            },
            {
                "time": "10:30",
                "event": "WTA - MADRID : Sasnovich A. vs Li A.",
                "channels": []
            },
            {
                "time": "10:30",
                "event": "WTA - MADRID : Sevastova A. vs Pavlyuchenkova A.",
                "channels": []
            },
            {
                "time": "12:00",
                "event": "WTA - MADRID : Volynets K. vs Kvitova P.",
                "channels": []
            },
            {
                "time": "12:00",
                "event": "WTA - MADRID : Carle M. L. vs Sramkova R.",
                "channels": []
            },
            {
                "time": "13:30",
                "event": "WTA - MADRID : Parks A. vs Jimenez Kasintseva V.",
                "channels": []
            },
            {
                "time": "13:30",
                "event": "WTA - MADRID : Pera B. vs Fett J.",
                "channels": []
            },
            {
                "time": "15:00",
                "event": "WTA - MADRID : Wang Xin. vs Sakkari M.",
                "channels": []
            },
            {
                "time": "15:00",
                "event": "WTA - MADRID : Bencic B. vs Sonmez Z.",
                "channels": []
            },
            {
                "time": "15:00",
                "event": "WTA - MADRID : Blinkova A. vs Udvardy P.",
                "channels": []
            },
            {
                "time": "15:00",
                "event": "WTA - MADRID : Krueger A. vs Potapova A.",
                "channels": []
            },
            {
                "time": "15:00",
                "event": "WTA - MADRID : Starodubtseva Y. vs Fruhvirtova L.",
                "channels": []
            },
            {
                "time": "15:00",
                "event": "WTA - MADRID : Tomljanovic A. vs Masarova R.",
                "channels": []
            },
            {
                "time": "15:00",
                "event": "WTA - MADRID : Lamens S. vs Raducanu E.",
                "channels": []
            },
            {
                "time": "15:00",
                "event": "WTA - MADRID : Jones F. vs Yastremska D.",
                "channels": []
            },
            {
                "time": "15:00",
                "event": "WTA - MADRID : Kudermetova V. vs Kudermetova P.",
                "channels": []
            },
            {
                "time": "15:00",
                "event": "WTA - MADRID : Uchijima M. vs Montgomery R.",
                "channels": []
            },
            {
                "time": "15:00",
                "event": "WTA - MADRID : Azarenka V. vs Danilovic O.",
                "channels": []
            },
            {
                "time": "15:00",
                "event": "WTA - MADRID : Cristian J. vs Kartal S.",
                "channels": []
            },
            {
                "time": "15:00",
                "event": "WTA - MADRID : Lys E. vs Kostovic T.",
                "channels": []
            },
            {
                "time": "15:00",
                "event": "WTA - MADRID : Kessler M. vs Andreescu B.",
                "channels": []
            }
        ],
        "Tennis</span>": [
            {
                "time": "09:00",
                "event": "2025 Mutua Madrid Open Tennis WTA First Round",
                "channels": []
            },
            {
                "time": "04:30",
                "event": "Challenger - Gwangju (KOR) - Double : F.Sun/K.Uchida vs M.Sharipov/I.Simakin",
                "channels": []
            },
            {
                "time": "04:30",
                "event": "Challenger - Gwangju (KOR) - Double : J.Delaney/Y.Shimizu vs B.Bayldon/R.Stalder",
                "channels": []
            },
            {
                "time": "04:30",
                "event": "Challenger - Gwangju (KOR) - Double : Y.H.Hsu/R.Noguchi vs S.Kwon/U.Park",
                "channels": []
            },
            {
                "time": "04:30",
                "event": "Challenger - Gwangju (KOR) : Yi Zhou vs Omar Jasika",
                "channels": []
            },
            {
                "time": "05:30",
                "event": "Challenger - Gwangju (KOR) - Double : A.Escoffier/L.Sanchez vs R.Ramanathan/A.Wang",
                "channels": []
            },
            {
                "time": "05:30",
                "event": "Challenger - Gwangju (KOR) : Adam Walton vs Marat Sharipov",
                "channels": []
            },
            {
                "time": "05:30",
                "event": "Challenger - Gwangju (KOR) : Hugo Grenier vs Li Tu",
                "channels": []
            },
            {
                "time": "05:30",
                "event": "Challenger - Gwangju (KOR) : Jason Kubler vs Soonwoo Kwon",
                "channels": []
            },
            {
                "time": "05:30",
                "event": "Challenger - Gwangju (KOR) : Kaichi Uchida vs Yasutaka Uchiyama",
                "channels": []
            },
            {
                "time": "05:40",
                "event": "Challenger - Gwangju (KOR) - Double : K.Pearson/J.K.Trotter vs V.Kirkov/B.Stevens",
                "channels": []
            },
            {
                "time": "05:40",
                "event": "Challenger - Gwangju (KOR) - Double : R.Ho/M.C.Romios vs Suk Ann/Jeamoon Lee",
                "channels": []
            },
            {
                "time": "05:40",
                "event": "Challenger - Gwangju (KOR) - Double : R.Sakamoto/S.Shimabukuro vs J.Delaney/A.Kachmazov",
                "channels": []
            },
            {
                "time": "06:00",
                "event": "UTR (F) - Bucuresti (ROM) : Alexandra Ignatik vs Cristiana Nicoleta Todoni",
                "channels": []
            },
            {
                "time": "06:50",
                "event": "Challenger - Gwangju (KOR) - Double : D.Cukierman/J.Paris vs J.Nam/K.Uesugi",
                "channels": []
            },
            {
                "time": "07:15",
                "event": "UTR (F) - Bucuresti (ROM) : Alisa Bianca Apostol vs Ioana Teodora Sava",
                "channels": []
            },
            {
                "time": "07:15",
                "event": "UTR (F) - Bucuresti (ROM) : Daria Lodikova vs Elena Ruxandra Bertea",
                "channels": []
            },
            {
                "time": "08:00",
                "event": "Challenger - Rome (ITA) : Francesco Maestrelli vs Lorenzo Carboni",
                "channels": []
            },
            {
                "time": "08:00",
                "event": "Challenger - Roma (ITA) - Double : L.Hignett/J.Mackinlay vs E.Grevelius/A.Heinonen",
                "channels": []
            },
            {
                "time": "08:00",
                "event": "Challenger - Rome (ITA) : Lukas Pokorny vs Lukas Neumayer",
                "channels": []
            },
            {
                "time": "08:30",
                "event": "UTR (F) - Bucuresti (ROM) : Darya Velikova vs Anastasia Safta",
                "channels": []
            },
            {
                "time": "08:30",
                "event": "ITF (M) - St. Margherita Di P. (ITA) : Marcello Serafini vs Andrea Picchione",
                "channels": []
            },
            {
                "time": "08:30",
                "event": "UTR (F) - Bucuresti (ROM) : Simona Ogescu vs Tara Mihaljevic",
                "channels": []
            },
            {
                "time": "09:30",
                "event": "Challenger - Rome (ITA) : Andrea Pellegrino vs Remy Bertola",
                "channels": []
            },
            {
                "time": "09:30",
                "event": "Challenger - Rome (ITA) : Federico Arnaboldi vs Dimitar Kuzmanov",
                "channels": []
            },
            {
                "time": "09:30",
                "event": "Challenger - Rome (ITA) : Vilius Gaubas vs Oleg Prihodko",
                "channels": []
            },
            {
                "time": "10:00",
                "event": "Challenger - Abidjan (CIV) : Aleksandre Bakshi vs Robin Bertrand",
                "channels": []
            },
            {
                "time": "10:00",
                "event": "Challenger - Abidjan (CIV) : Michael Geerts vs Dominik Kellovsky",
                "channels": []
            },
            {
                "time": "10:00",
                "event": "Challenger - Abidjan (CIV) - Double : P.Henning/K.van Wyk vs C.Chidekh/H.J.Maginley",
                "channels": []
            },
            {
                "time": "10:40",
                "event": "Challenger - Roma (ITA) - Double : F.Maestrelli/G.Pennaforti vs M.Hermans/T.Pereira",
                "channels": []
            },
            {
                "time": "10:40",
                "event": "Challenger - Rome (ITA) : Sandro Kopp vs Hady Habib",
                "channels": []
            },
            {
                "time": "10:40",
                "event": "Challenger - Rome (ITA) : Timofey Skatov vs Stefano Travaglia",
                "channels": []
            },
            {
                "time": "11:10",
                "event": "Challenger - Abidjan (CIV) : Aryan Shah vs Ergi Kirkin",
                "channels": []
            },
            {
                "time": "11:50",
                "event": "Challenger - Roma (ITA) - Double : F.Reynolds/J.Watt vs J.Eysseric/A.Pellegrino",
                "channels": []
            },
            {
                "time": "11:50",
                "event": "Challenger - Roma (ITA) - Double : S.Agostini/K.Stevenson vs J.Bilardo/J.Vasami",
                "channels": []
            },
            {
                "time": "12:10",
                "event": "Challenger - Roma (ITA) - Double : F.Arnaboldi/R.Bertola vs S.Banthia/A.Donski",
                "channels": []
            },
            {
                "time": "12:20",
                "event": "Challenger - Abidjan (CIV) - Double : S.K.R.Ganta/A.Kalyanpur vs S.Andre/M.Y.H.Kouame",
                "channels": []
            },
            {
                "time": "13:00",
                "event": "Challenger - San Miguel de Tucuman (ARG) : Alex Barrena vs Nicolas Kicker",
                "channels": []
            },
            {
                "time": "13:00",
                "event": "Challenger - Abidjan (CIV) - Double : V.Ursu/D.Wenger vs K.Bittoun/Ouakaa",
                "channels": []
            },
            {
                "time": "13:10",
                "event": "Challenger - Abidjan (CIV) - Double : M.Echargui/L.Potenza vs M.Geerts/J.Seeman",
                "channels": []
            },
            {
                "time": "13:30",
                "event": "Challenger - Abidjan (CIV) - Double : A.Shah/P.Somani vs T.Colson/A.Lobanov",
                "channels": []
            },
            {
                "time": "14:10",
                "event": "Challenger - San Miguel de Tucuman (ARG) : Mariano Kestelboim vs Alvaro Guillen Meza",
                "channels": []
            },
            {
                "time": "14:20",
                "event": "Challenger - Abidjan (CIV) - Double : J.J.Bianchi/B.Perez vs A.Bakshi/S.D.P.Dev",
                "channels": []
            },
            {
                "time": "14:30",
                "event": "Challenger - Rome (ITA) : Matteo Gigante vs Kimmer Coppejans",
                "channels": []
            },
            {
                "time": "15:00",
                "event": "Challenger - Abidjan (CIV) - Double : Y.Erel/E.Kirkin vs A.Genov/T.Hands",
                "channels": []
            },
            {
                "time": "16:00",
                "event": "ITF (F) - Oeiras (POR) - Double : E.Appleton/Q.Tang vs E.Pridankina/E.Silva",
                "channels": []
            },
            {
                "time": "16:00",
                "event": "ITF (F) - Oeiras (POR) - Double : F.Jorge/M.Jorge vs M.Skoch/J.Maleckova",
                "channels": []
            },
            {
                "time": "16:00",
                "event": "Challenger - Double : L.Aboian/V.Aboian vs V.Orlov/G.Roveri Sidney",
                "channels": []
            },
            {
                "time": "17:10",
                "event": "Challenger - Double : M.Kestelboim/G.Villanueva vs I.Carou/M.Dellien",
                "channels": []
            },
            {
                "time": "18:10",
                "event": "Challenger - San Miguel de Tucuman (ARG) : Santiago Rodriguez Taverna vs Juan Estevez",
                "channels": []
            },
            {
                "time": "18:20",
                "event": "Challenger - Double : G.I.Justo/R.Olivo vs L.Britto/J.E.Schiessl",
                "channels": []
            },
            {
                "time": "22:00",
                "event": "Challenger - Double : L.E.Ambrogi/M.Zeitune vs A.Guillen Meza/I.Monzon",
                "channels": []
            }
        ],
        "WWE</span>": [
            {
                "time": "00:00",
                "event": "All Elite Wrestling: Dynamite",
                "channels": []
            }
        ],
        "Combat sports</span>": [
            {
                "time": "07:00",
                "event": "Judo: European Championships European Championships. Day 1. Qualifying.",
                "channels": []
            },
            {
                "time": "14:00",
                "event": "Judo: European Championships European Championships. Day 1. Finals.",
                "channels": []
            },
            {
                "time": "14:30",
                "event": "Sambo : European Championship",
                "channels": []
            }
        ],
        "Snooker</span>": [
            {
                "time": "09:00",
                "event": "World Snooker Championship - Round 1",
                "channels": []
            },
            {
                "time": "13:30",
                "event": "World Snooker Championship : Brecel, Luca vs. Day, Ryan",
                "channels": []
            },
            {
                "time": "18:00",
                "event": "World Snooker Championship : Selby, Mark vs. Woollaston, Ben",
                "channels": []
            }
        ],
        "Baseball</span>": [
            {
                "time": "16:00",
                "event": "Minor League Baseball : Syracuse Mets vs Worcester Red Sox",
                "channels": []
            },
            {
                "time": "18:30",
                "event": "Minor League Baseball : Syracuse Mets vs Worcester Red Sox",
                "channels": []
            },
            {
                "time": "00:00",
                "event": "College Softball : Texas vs Oklahoma State",
                "channels": []
            },
            {
                "time": "16:15",
                "event": "MLB : St. Louis Cardinals vs Atlanta Braves",
                "channels": []
            },
            {
                "time": "17:10",
                "event": "MLB : Cincinnati Reds vs Miami Marlins",
                "channels": []
            },
            {
                "time": "17:10",
                "event": "MLB : New York Yankees vs Cleveland Guardians",
                "channels": []
            },
            {
                "time": "17:10",
                "event": "MLB : Philadelphia Phillies vs New York Mets",
                "channels": []
            },
            {
                "time": "17:10",
                "event": "MLB : San Diego Padres vs Detroit Tigers",
                "channels": []
            },
            {
                "time": "22:45",
                "event": "MLB : Baltimore Orioles vs Washington Nationals",
                "channels": []
            },
            {
                "time": "22:45",
                "event": "MLB : Seattle Mariners vs Boston Red Sox",
                "channels": []
            },
            {
                "time": "23:00",
                "event": "MLB : Los Angeles Dodgers vs Chicago Cubs",
                "channels": []
            },
            {
                "time": "23:40",
                "event": "MLB : Chicago White Sox vs Minnesota Twins",
                "channels": []
            },
            {
                "time": "23:40",
                "event": "MLB : Colorado Rockies vs Kansas City Royals",
                "channels": []
            },
            {
                "time": "23:40",
                "event": "MLB : Toronto Blue Jays vs Houston Astros",
                "channels": []
            },
            {
                "time": "01:38",
                "event": "MLB : Pittsburgh Pirates vs Los Angeles Angels",
                "channels": []
            },
            {
                "time": "01:40",
                "event": "MLB : Tampa Bay Rays vs Arizona Diamondbacks",
                "channels": []
            },
            {
                "time": "01:45",
                "event": "MLB : Milwaukee Brewers vs San Francisco Giants",
                "channels": []
            },
            {
                "time": "02:05",
                "event": "MLB : Texas Rangers vs Oakland Athletics",
                "channels": []
            }
        ],
        "Basketball</span>": [
            {
                "time": "09:00",
                "event": "Philippines - PBA Cup : NLEX Road Warriors vs TNT Katropa",
                "channels": []
            },
            {
                "time": "10:00",
                "event": "Spain - LEB Oro : CB Zamora vs Menorca",
                "channels": []
            },
            {
                "time": "11:30",
                "event": "Philippines - PBA Cup : Dyip vs Barangay Ginebra",
                "channels": []
            },
            {
                "time": "11:35",
                "event": "China - CBA : Zhejiang Guangsha Lions vs Qingdao Eagles",
                "channels": []
            },
            {
                "time": "14:00",
                "event": "Russia Super League : Khimki M. vs CSKA Moscow 2",
                "channels": []
            },
            {
                "time": "15:00",
                "event": "Czech Republic NBL Playoffs : Sokol Pisek vs. BK Decin",
                "channels": []
            },
            {
                "time": "15:00",
                "event": "Liga Nationala : Cluj Napoca vs Valcea",
                "channels": []
            },
            {
                "time": "15:30",
                "event": "Lithuania - LKL : Sintek Jonava vs Juventus Utena",
                "channels": []
            },
            {
                "time": "16:30",
                "event": "ussia United League : CSKA Moscow vs Pari Nizhny Novgorod",
                "channels": []
            },
            {
                "time": "16:30",
                "event": "Champions League : AEK Athens vs Nanterre",
                "channels": []
            },
            {
                "time": "16:45",
                "event": "LFB Women : Lattes Montpellier W vs Flammes Carolo W",
                "channels": []
            },
            {
                "time": "17:00",
                "event": "Euroleague : Monaco vs Barcelona",
                "channels": []
            },
            {
                "time": "17:00",
                "event": "Spain - LEB Oro : San Pablo Burgos vs Fuenlabrada",
                "channels": []
            },
            {
                "time": "17:15",
                "event": "FIBA Europe Cup : PAOK vs Bilbao",
                "channels": []
            },
            {
                "time": "17:30",
                "event": "Swiss - LNA - Playoff : BBC Nyon vs SAM Massagno",
                "channels": []
            },
            {
                "time": "17:30",
                "event": "Swiss - LNA - Playoff : Fribourg Olympic vs Monthey",
                "channels": []
            },
            {
                "time": "18:00",
                "event": "SLB : Manchester Basketball vs Surrey 89ers",
                "channels": []
            },
            {
                "time": "18:30",
                "event": "Euroleague : Olympiakos vs Real Madrid",
                "channels": []
            },
            {
                "time": "18:30",
                "event": "Slovenian League (W): Playoff - Final (G3) : Celje vs Triglav",
                "channels": []
            },
            {
                "time": "18:30",
                "event": "Italy - Serie A2 : Fortitudo Bologna vs Rimini",
                "channels": []
            },
            {
                "time": "18:30",
                "event": "England - SLB : London Lions vs Leicester Riders",
                "channels": []
            },
            {
                "time": "18:45",
                "event": "Spain - LEB Oro : Oviedo vs Real Valladolid",
                "channels": []
            },
            {
                "time": "18:50",
                "event": "LFB Women : Landes W vs Lyon W",
                "channels": []
            },
            {
                "time": "19:15",
                "event": "Iceland Women's Basketball Premier League : Keflavik vs UMF Njardvik",
                "channels": []
            },
            {
                "time": "19:45",
                "event": "FIBA CHAMPIONS LEAGUE : Tenerife vs Tortona",
                "channels": []
            },
            {
                "time": "22:30",
                "event": "Brazil - NBB - Playoff : Sao Jose vs Vasco da Gama",
                "channels": []
            },
            {
                "time": "23:30",
                "event": "Brazil - NBB - Playoff : Caxias do Sul vs Flamengo",
                "channels": []
            },
            {
                "time": "00:30",
                "event": "Argentina - LNB : Instituto Cordoba vs San Martin Corrientes",
                "channels": []
            },
            {
                "time": "00:40",
                "event": "Argentina - LLA : Amancay de La Rioja vs Independiente Santiago Estero",
                "channels": []
            },
            {
                "time": "23:00",
                "event": "NBA : Orlando Magic vs Boston Celtics",
                "channels": []
            },
            {
                "time": "23:30",
                "event": "NBA : Miami Heat vs Cleveland Cavaliers",
                "channels": []
            },
            {
                "time": "01:30",
                "event": "NBA : Golden State Warriors vs Houston Rockets",
                "channels": []
            }
        ],
        "Cycling</span>": [
            {
                "time": "10:30",
                "event": "Tour of the Alps | Stage 3 Men | Sterzing \u2013 Innichen (145.5km)",
                "channels": []
            },
            {
                "time": "10:40",
                "event": "Tour of the Thousands on Bikes: Day Three",
                "channels": []
            },
            {
                "time": "10:45",
                "event": "Fleche Wallonne Men | Ciney - Huy (205.2km)",
                "channels": []
            },
            {
                "time": "14:45",
                "event": "Fleche Wallonne Women | Huy (140.7km)",
                "channels": []
            }
        ],
        "Futsal</span>": [
            {
                "time": "13:00",
                "event": "Futsal Romanian Cup F4 : Odorheiu Secuiesc vs Mausoleul Marasesti",
                "channels": []
            }
        ],
        "Handball</span>": [
            {
                "time": "16:00",
                "event": "Slovakia Extraliga : MHC Start Nove Zamky vs. HT Tatran Presov",
                "channels": []
            },
            {
                "time": "16:15",
                "event": "Norway Eliteserien : Kolstad Handball vs. Naerboe IL",
                "channels": []
            },
            {
                "time": "16:30",
                "event": "Bambusa Kvindeligaen : Herning-Ikast Haandbold vs. Soenderjyske HK",
                "channels": []
            },
            {
                "time": "16:45",
                "event": "Champions League : SC Magdeburg vs. Veszprem KC",
                "channels": []
            },
            {
                "time": "18:30",
                "event": "Champions League : Wybrzeze Gdansk vs Ostrow Wielkopolski",
                "channels": []
            },
            {
                "time": "18:30",
                "event": "Bambusa Kvindeligaen : HC Odense vs. Copenhagen Handball",
                "channels": []
            },
            {
                "time": "18:45",
                "event": "Champions League : HBC Nantes vs. Sporting Clube Portugal",
                "channels": []
            }
        ],
        "Horse Racing</span>": [
            {
                "time": "15:30",
                "event": "Live racing from around the UK",
                "channels": []
            },
            {
                "time": "17:00",
                "event": "America's Day at the Races",
                "channels": []
            }
        ],
        "Ice Hockey</span>": [
            {
                "time": "14:00",
                "event": "KHL : Salavat Yulaev Ufa vs Spartak Moscow",
                "channels": []
            },
            {
                "time": "16:30",
                "event": "KHL : Lokomotiv Yaroslavl vs Avangard Omsk",
                "channels": []
            },
            {
                "time": "16:00",
                "event": "Slovakia Extralig : HK Nitra vs. HC Kosice",
                "channels": []
            },
            {
                "time": "19:00",
                "event": "WCH U18 : Sweden U18 vs Switzerland U18",
                "channels": []
            },
            {
                "time": "00:00",
                "event": "WCH U18 : Czech Republic U18 vs USA U18",
                "channels": []
            },
            {
                "time": "17:30",
                "event": "Hockey. Fonbet KHL Championship. 1/4 finals",
                "channels": []
            },
            {
                "time": "18:00",
                "event": "SHL : Lulea Hockey vs. Brynas IF",
                "channels": []
            },
            {
                "time": "17:30",
                "event": "DEL : K\u00f6lner Haie vs Eisb\u00e4ren Berlin",
                "channels": []
            },
            {
                "time": "23:00",
                "event": "NHL : Montr\u00e9al Canadiens vs Washington Capitals",
                "channels": []
            },
            {
                "time": "01:30",
                "event": "NHL : Dallas Stars vs Colorado Avalanche",
                "channels": []
            },
            {
                "time": "02:00",
                "event": "NHL : Edmonton Oilers vs Los Angeles Kings",
                "channels": []
            }
        ],
        "Squash</span>": [
            {
                "time": "11:00",
                "event": "A1 Padel: Lanzarote Open (T2025): Round of 16 - Day 1",
                "channels": []
            }
        ],
        "Lacrosse</span>": [
            {
                "time": "15:00",
                "event": "Women's College Lacrosse : Virginia Tech vs North Carolina",
                "channels": []
            },
            {
                "time": "18:00",
                "event": "Women's College Lacrosse : Clemson vs Duke",
                "channels": []
            },
            {
                "time": "21:00",
                "event": "Women's College Lacrosse : Virginia vs Boston College",
                "channels": []
            },
            {
                "time": "00:00",
                "event": "Women's College Lacrosse : Syracuse vs Stanford",
                "channels": []
            }
        ],
        "Volleyball</span>": [
            {
                "time": "14:00",
                "event": "T\u00fcrkiye First Division : Ziraat Bankas\u0131 vs Galatasaray",
                "channels": []
            },
            {
                "time": "15:30",
                "event": "PlusLiga : Warta Zawiercie vs. Projekt Warsawa",
                "channels": []
            },
            {
                "time": "15:30",
                "event": "Austria, 1. Bundesliga Women : VB NO Sokol/Post vs. UVC Holding Graz",
                "channels": []
            },
            {
                "time": "16:00",
                "event": "Slovenian league (w): Playoff - FINALE (G3) : Calcit Kamnik vs Branik Maribor",
                "channels": []
            },
            {
                "time": "16:00",
                "event": "Volley League : Panathinaikos vs Olympiacos",
                "channels": []
            },
            {
                "time": "17:00",
                "event": "Czech Republic Extraliga : Vk Lvi Praha vs. VK CEZ Karlovarsko",
                "channels": []
            },
            {
                "time": "17:00",
                "event": "German league (W): Playoff - FINALE (G2) : Dresden vs Schwerin",
                "channels": []
            },
            {
                "time": "18:00",
                "event": "Croatia Superliga, Women : Mladost Zagreb vs. Ok Dinamo",
                "channels": []
            },
            {
                "time": "18:20",
                "event": "Austria 1. Bundesliga : TSV Hartberg vs. Tirol Volleyballteam",
                "channels": []
            },
            {
                "time": "18:30",
                "event": "PlusLiga : Lkps Lublin vs. Jastrzebski Wegiel",
                "channels": []
            }
        ],
        "Water polo</span>": [
            {
                "time": "18:00",
                "event": "LEN Champions League : Vk Jadran Split vs. CN Marseille",
                "channels": []
            },
            {
                "time": "18:00",
                "event": "LEN Champions League : Vk Novi Beograd vs. Olympiakos",
                "channels": []
            }
        ],
        "Water Sports</span>": [
            {
                "time": "21:00",
                "event": "Maria Lenk Swimming Trophy Finals",
                "channels": []
            }
        ]
    }
}